.DS_Store
SHFS/DFwrapper.py
SHFS/FeatureSelectionClf.py
SHFS/FeatureSelectionRegression.py
SHFS/FeatureSelectionUniversal.py
SHFS/__about__.py
SHFS/__init__.py
SHFS-0.1.5.dist-info/METADATA
SHFS-0.1.5.dist-info/WHEEL
SHFS-0.1.5.dist-info/top_level.txt
SHFS-0.1.5.dist-info/RECORD
