Metadata-Version: 2.1
Name: SHFS
Version: 0.1.5
Summary: Feature election group of classes calculate the importance of features based on the Shap library for the classification and regression problem Only works with randomforest models for efficiency or gradient boosting models. DFwrapper - remove multicollinearity and outliers
Home-page: https://github.com/ArtyKrafty/featureselectors
Author: Artem, et al.
Author-email: artysolomko@gmail.com
License: UNKNOWN
Keywords: shap,fi,pipeline
Platform: UNKNOWN
Classifier: Environment :: Console
Classifier: Natural Language :: English
Classifier: Development Status :: 3 - Alpha
Classifier: Intended Audience :: Developers
Classifier: Operating System :: OS Independent
Classifier: Programming Language :: Python :: 3
Requires-Python: >=3.6
Requires-Dist: pandas
Requires-Dist: numpy
Requires-Dist: scikit-learn (==1.0.1)
